c3/__init__.py
c3/c3objs.py
c3/experiment.py
c3/main.py
c3/model.py
c3/parametermap.py
c3/generator/__init__.py
c3/generator/devices.py
c3/generator/generator.py
c3/libraries/__init__.py
c3/libraries/algorithms.py
c3/libraries/chip.py
c3/libraries/constants.py
c3/libraries/envelopes.py
c3/libraries/estimators.py
c3/libraries/fidelities.py
c3/libraries/hamiltonians.py
c3/libraries/propagation.py
c3/libraries/sampling.py
c3/libraries/tasks.py
c3/optimizers/__init__.py
c3/optimizers/calibration.py
c3/optimizers/modellearning.py
c3/optimizers/optimalcontrol.py
c3/optimizers/optimalcontrol_robust.py
c3/optimizers/optimizer.py
c3/optimizers/sensitivity.py
c3/qiskit/__init__.py
c3/qiskit/c3_backend.py
c3/qiskit/c3_backend_utils.py
c3/qiskit/c3_exceptions.py
c3/qiskit/c3_job.py
c3/qiskit/c3_provider.py
c3/signal/__init__.py
c3/signal/gates.py
c3/signal/pulse.py
c3/utils/__init__.py
c3/utils/log_reader.py
c3/utils/qt_utils.py
c3/utils/tf_utils.py
c3/utils/utils.py
c3_toolset-1.4.dist-info/AUTHORS
c3_toolset-1.4.dist-info/LICENSE
c3_toolset-1.4.dist-info/METADATA
c3_toolset-1.4.dist-info/WHEEL
c3_toolset-1.4.dist-info/top_level.txt
c3_toolset-1.4.dist-info/RECORD
